reolinkapi/__init__.py
reolinkapi/camera.py
reolinkapi/handlers/__init__.py
reolinkapi/handlers/api_handler.py
reolinkapi/handlers/rest_handler.py
reolinkapi/mixins/__init__.py
reolinkapi/mixins/alarm.py
reolinkapi/mixins/device.py
reolinkapi/mixins/display.py
reolinkapi/mixins/download.py
reolinkapi/mixins/image.py
reolinkapi/mixins/motion.py
reolinkapi/mixins/network.py
reolinkapi/mixins/nvrdownload.py
reolinkapi/mixins/ptz.py
reolinkapi/mixins/record.py
reolinkapi/mixins/stream.py
reolinkapi/mixins/system.py
reolinkapi/mixins/user.py
reolinkapi/mixins/zoom.py
reolinkapi/utils/__init__.py
reolinkapi/utils/rtsp_client.py
reolinkapi/utils/util.py
reolinkapi-0.4.0.dist-info/LICENSE.md
reolinkapi-0.4.0.dist-info/METADATA
reolinkapi-0.4.0.dist-info/WHEEL
reolinkapi-0.4.0.dist-info/top_level.txt
reolinkapi-0.4.0.dist-info/RECORD
