Metadata-Version: 2.1
Name: reolinkapi
Version: 0.4.0
Summary: Reolink Camera API client written in Python 3
Home-page: https://github.com/ReolinkCameraAPI/reolinkapipy
Author: Benehiko
Author-email: alanoterblanche@gmail.com
License: GPL-3.0
Requires-Python: >=3.12.4
License-File: LICENSE.md
Requires-Dist: setuptools
Requires-Dist: PySocks ==1.7.1
Requires-Dist: PyYaml ==6.0.2
Requires-Dist: requests >=2.32.3
Provides-Extra: streaming
Requires-Dist: numpy ==2.0.1 ; extra == 'streaming'
Requires-Dist: opencv-python ==4.10.0.84 ; extra == 'streaming'
Requires-Dist: Pillow ==10.4.0 ; extra == 'streaming'
